tornadose/__init__.py
tornadose/handlers.py
tornadose/stores.py
tornadose-0.4.1.dist-info/DESCRIPTION.rst
tornadose-0.4.1.dist-info/METADATA
tornadose-0.4.1.dist-info/RECORD
tornadose-0.4.1.dist-info/WHEEL
tornadose-0.4.1.dist-info/metadata.json
tornadose-0.4.1.dist-info/top_level.txt
