Metadata-Version: 2.0
Name: tornadose
Version: 0.4.1
Summary: Tornado-sent events
Home-page: https://github.com/mivade/tornadose
Author: Michael V. DePalatis
Author-email: mike@depalatis.net
License: MIT
Keywords: tornado web eventsource websockets pubsub
Platform: UNKNOWN
Classifier: Development Status :: 5 - Production/Stable
Classifier: Programming Language :: Python
Classifier: Programming Language :: Python :: 2.7
Classifier: Programming Language :: Python :: 3.3
Classifier: Programming Language :: Python :: 3.4
Classifier: Programming Language :: Python :: 3.5
Classifier: Programming Language :: Python :: Implementation :: PyPy
Classifier: Topic :: Internet :: WWW/HTTP :: Dynamic Content
Classifier: Intended Audience :: Developers
Classifier: License :: OSI Approved :: MIT License
Requires-Dist: tornado (>=4.2)
